{
  "descriptionHash": "1EB88340B0461301ABA0771316DCD73ECA655CA0EF4E23C94D007B99C359C983ACCAC04E162D6F1A2C85FAA5689552A5F6604174E189DBC5670739D5162E6A54",
  "descriptionLocation": "/mnt/vss/_work/1/s/msgraph-metadata/clean_beta_openapi/openapi.yaml",
  "lockFileVersion": "1.0.0",
  "kiotaVersion": "1.5.0",
  "clientClassName": "BaseGraphServiceClient",
  "clientNamespaceName": "Microsoft.Graph.Beta",
  "language": "CSharp",
  "usesBackingStore": true,
  "includeAdditionalData": true,
  "serializers": [
    "Microsoft.Kiota.Serialization.Json.JsonSerializationWriterFactory",
    "Microsoft.Kiota.Serialization.Text.TextSerializationWriterFactory",
    "Microsoft.Kiota.Serialization.Form.FormSerializationWriterFactory"
  ],
  "deserializers": [
    "Microsoft.Kiota.Serialization.Json.JsonParseNodeFactory",
    "Microsoft.Kiota.Serialization.Text.TextParseNodeFactory",
    "Microsoft.Kiota.Serialization.Form.FormParseNodeFactory"
  ],
  "structuredMimeTypes": [
    "application/json",
    "text/plain",
    "application/x-www-form-urlencoded"
  ],
  "includePatterns": [],
  "excludePatterns": [],
  "disabledValidationRules": []
}