{
  "descriptionHash": "0EC7F4FFBC296C5594F3351506BAA95679A71EE2BDC0464710C399C6EA0ECAA38F140CE3CADB09F860FCEE233974991BAA9F5D81A2EB562570D4B8F0EE6D8C98",
  "descriptionLocation": "../../msgraph-metadata/clean_beta_openapi/openapi.yaml",
  "lockFileVersion": "1.0.0",
  "kiotaVersion": "1.19.0",
  "clientClassName": "BaseGraphServiceClient",
  "typeAccessModifier": "Public",
  "clientNamespaceName": "Microsoft.Graph.Beta",
  "language": "CSharp",
  "usesBackingStore": true,
  "excludeBackwardCompatible": false,
  "includeAdditionalData": true,
  "disableSSLValidation": false,
  "serializers": [
    "Microsoft.Kiota.Serialization.Json.JsonSerializationWriterFactory",
    "Microsoft.Kiota.Serialization.Text.TextSerializationWriterFactory",
    "Microsoft.Kiota.Serialization.Form.FormSerializationWriterFactory",
    "Microsoft.Kiota.Serialization.Multipart.MultipartSerializationWriterFactory"
  ],
  "deserializers": [
    "Microsoft.Kiota.Serialization.Json.JsonParseNodeFactory",
    "Microsoft.Kiota.Serialization.Text.TextParseNodeFactory",
    "Microsoft.Kiota.Serialization.Form.FormParseNodeFactory"
  ],
  "structuredMimeTypes": [
    "application/json",
    "text/plain;q=0.9",
    "application/x-www-form-urlencoded;q=0.2",
    "multipart/form-data;q=0.1"
  ],
  "includePatterns": [],
  "excludePatterns": [],
  "disabledValidationRules": []
}